README.rst
pyproject.toml
setup.py
fmi/__init__.py
fmi/__version__.py
fmi/constant.py
fmi/fmi.py
fmi/model.py
fmi/py.typed
fmi/wfs_parse.py
fmi.py.egg-info/PKG-INFO
fmi.py.egg-info/SOURCES.txt
fmi.py.egg-info/dependency_links.txt
fmi.py.egg-info/requires.txt
fmi.py.egg-info/top_level.txt
test/test_api.py
test/test_functional.py
test/test_model.py
test/test_wfs_parser.py