Metadata-Version: 1.2
Name: fmi.py
Version: 1.1.1
Summary: Finnish Meteorological Institute API wrapper
Home-page: https://www.github.com/je-l/fmi.py
Author: je-l
License: UNKNOWN
Platform: UNKNOWN
Classifier: Development Status :: 5 - Production/Stable
Classifier: Programming Language :: Python :: 3.7
Classifier: Programming Language :: Python :: 3.8
Classifier: Programming Language :: Python :: 3.9
Classifier: Programming Language :: Python :: 3.10
Classifier: Framework :: AsyncIO
Classifier: Typing :: Typed
Requires-Python: >=3.6
